setup.cfg
setup.py
baidu/__init__.py
baidu/baidu.py
baidu/baidu_tests.py
baidu.egg-info/PKG-INFO
baidu.egg-info/SOURCES.txt
baidu.egg-info/dependency_links.txt
baidu.egg-info/entry_points.txt
baidu.egg-info/not-zip-safe
baidu.egg-info/top_level.txt