Metadata-Version: 1.0
Name: baidu
Version: 0.2
Summary: A English-Chinese translator running in terminal
Home-page: https://github.com/OldPanda/Baidu-Translator
Author: OldPanda
Author-email: zjh0930@gmail.com
License: UNKNOWN
Keywords: python baidu translate
Platform: UNKNOWN
